MANIFEST.in
requirements.txt
setup.cfg
setup.py
decision_tree_id3.egg-info/PKG-INFO
decision_tree_id3.egg-info/SOURCES.txt
decision_tree_id3.egg-info/dependency_links.txt
decision_tree_id3.egg-info/requires.txt
decision_tree_id3.egg-info/top_level.txt
id3/__init__.py
id3/export.py
id3/id3.py
id3/node.py
id3/splitter.py
id3/tree.py
id3/data/__init__.py
id3/data/load_data.py
id3/tests/__init__.py
id3/tests/test_common.py
id3/tests/test_data.py
id3/tests/test_export.py
id3/tests/test_id3.py
id3/tests/test_utils.py
id3/utils/__init__.py
id3/utils/array_operations.py
id3/utils/checks.py
id3/utils/extended_label_encoder.py