Metadata-Version: 1.0
Name: decision-tree-id3
Version: 0.0.2
Summary: A scikit-learn compatible package for id3 decision tree
Home-page: UNKNOWN
Author: Daniel Pettersson, Otto Nordander
Author-email: svaante@gmail.com, otto.nordander@gmail.com
License: UNKNOWN
Platform: UNKNOWN
